estimenergy_client/__init__.py
estimenergy_client/client.py
estimenergy_client-1.4.1.dist-info/LICENSE
estimenergy_client-1.4.1.dist-info/METADATA
estimenergy_client-1.4.1.dist-info/WHEEL
estimenergy_client-1.4.1.dist-info/top_level.txt
estimenergy_client-1.4.1.dist-info/RECORD
