Metadata-Version: 2.1
Name: estimenergy-client
Version: 1.4.1
Summary: Client for the Estimenergy API
Home-page: https://github.com/eulemitkeule/estimenergy
Author: Lennard Beers
Author-email: l.beers@outlook.de
Keywords: estimenergy api client
Requires-Python: >=3.6
License-File: LICENSE
Requires-Dist: requests
